PyFFD/__init__.py
PyFFD/ffd_builder.py
PyFFD/nurbs.py
PyFFD/vtktools.py
PyFFD-0.1.5.dist-info/LICENSE
PyFFD-0.1.5.dist-info/METADATA
PyFFD-0.1.5.dist-info/WHEEL
PyFFD-0.1.5.dist-info/top_level.txt
PyFFD-0.1.5.dist-info/RECORD
