Metadata-Version: 2.1
Name: PyFFD
Version: 0.1.5
Summary: Tools to create FFD operator from point cloud.
Author-email: Theo SENTAGNE <theo.sentagne@gmail.com>
Project-URL: Homepage, https://github.com/t-sentagne/PyFFD
Project-URL: Bug Tracker, https://github.com/t-sentagne/PyFFD/issues
Classifier: Programming Language :: Python :: 3
Classifier: Operating System :: OS Independent
Requires-Python: >=3.7
License-File: LICENSE
Requires-Dist: numpy
Requires-Dist: scipy
Requires-Dist: matplotlib
Requires-Dist: numba
